simpay/__init__.py
simpay/__version__.py
simpay/baseModel.py
simpay/simpay.py
simpay/directbilling/__init__.py
simpay/directbilling/client.py
simpay/directbilling/models.py
simpay/sms/__init__.py
simpay/sms/client.py
simpay/sms/models.py
simpay/sms_xml/__init__.py
simpay/sms_xml/client.py
simpay/sms_xml/models.py
simpay_api-3.0.1.dist-info/LICENSE
simpay_api-3.0.1.dist-info/METADATA
simpay_api-3.0.1.dist-info/WHEEL
simpay_api-3.0.1.dist-info/top_level.txt
simpay_api-3.0.1.dist-info/RECORD
