Metadata-Version: 2.1
Name: simpay-api
Version: 3.0.1
Summary: Python wrapper for Simpay API
Home-page: https://github.com/SimPaypl/SimPay-API-Python
Author: Rafał Więcek
Author-email: kontakt@simpay.pl
Requires-Python: >3.0
License-File: LICENSE
Requires-Dist: requests (>=2.26.0)
Requires-Dist: pydantic (>=1.10.7)
Provides-Extra: docs
Requires-Dist: sphinx (>=7.0.1) ; extra == 'docs'
